README.md
setup.py
chameleon/__init__.py
chameleon/__main__.py
chameleon/chameleon.py
chameleon/colors.py
chameleon/ui.py
moving_chameleon.egg-info/PKG-INFO
moving_chameleon.egg-info/SOURCES.txt
moving_chameleon.egg-info/dependency_links.txt
moving_chameleon.egg-info/entry_points.txt
moving_chameleon.egg-info/requires.txt
moving_chameleon.egg-info/top_level.txt